[
  {
    "id": "490",
    "name": "Frédéric•Petit",
    "born": "6 May 1857 in Carnières, Nord (FRA)",
    "measurements": {},
    "medals": [
      {
        "game": "1900 Summer Olympics",
        "noc": "FRA",
        "discipline": "Archery",
        "event": "Au Chapelet, 33 metres, Men\n(Olympic)",
        "medal": "Bronze"
      },
      {
        "game": "1900 Summer Olympics",
        "noc": "FRA",
        "discipline": "Archery",
        "event": "Au Cordon Doré, 33 metres, Men\n(Olympic)",
        "medal": "Bronze"
      }
    ]
  },
  {
    "id": "590",
    "name": "Richard•Priestman",
    "born": "16 July 1955 in Liverpool, England (GBR)",
    "measurements": "180 cm / 66 kg",
    "medals": [
      {
        "game": "1988 Summer Olympics",
        "noc": "GBR",
        "discipline": "Archery",
        "event": "Team, Men\n(Olympic)",
        "medal": "Bronze"
      },
      {
        "game": "1992 Summer Olympics",
        "noc": "GBR",
        "discipline": "Archery",
        "event": "Team, Men\n(Olympic)",
        "medal": "Bronze"
      }
    ]
  },
  {
    "id": "690",
    "name": "Natasha•Zverava",
    "born": "16 April 1971 in Minsk, Minsk (BLR)",
    "measurements": "172 cm / 60 kg",
    "medals": [
      {
        "game": "1992 Summer Olympics",
        "noc": "EUN",
        "discipline": "Tennis",
        "event": "Doubles, Women\n(Olympic)",
        "medal": "Bronze"
      }
    ]
  },
  {
    "id": "1090",
    "name": "Ivan•Mihaylov",
    "born": "25 December 1944 in Sliven, Sliven (BUL)",
    "measurements": "164 cm / 60 kg",
    "medals": [
      {
        "game": "1968 Summer Olympics",
        "noc": "BUL",
        "discipline": "Boxing",
        "event": "Featherweight, Men\n(Olympic)",
        "medal": "Bronze"
      }
    ]
  },
  {
    "id": "1490",
    "name": "José•Delgado",
    "born": "25 August 1960 in Meneses, Sancti Spíritus (CUB)",
    "measurements": "182 cm / 85 kg",
    "medals": [
      {
        "game": "1992 Summer Olympics",
        "noc": "CUB",
        "discipline": "Baseball (Baseball/Softball)",
        "event": "Baseball, Men\n(Olympic)",
        "medal": "Gold"
      }
    ]
  },
  {
    "id": "1590",
    "name": "Tadahito•Iguchi",
    "born": "4 December 1974 in Tanashi, Nishitokyo, Tokyo (JPN)",
    "measurements": "177 cm / 78 kg",
    "medals": [
      {
        "game": "1996 Summer Olympics",
        "noc": "JPN",
        "discipline": "Baseball (Baseball/Softball)",
        "event": "Baseball, Men\n(Olympic)",
        "medal": "Silver"
      }
    ]
  },
  {
    "id": "2190",
    "name": "Valentina•Kovpan",
    "born": "28 February 1950 in Petroostriv, Kirovohrad (UKR)",
    "measurements": "168 cm / 60 kg",
    "medals": [
      {
        "game": "1976 Summer Olympics",
        "noc": "URS",
        "discipline": "Archery",
        "event": "Individual, Women\n(Olympic)",
        "medal": "Silver"
      }
    ]
  },
  {
    "id": "4190",
    "name": "Bruno•Visintin",
    "born": "23 November 1932 in La Spezia, La Spezia (ITA)",
    "measurements": {},
    "medals": [
      {
        "game": "1952 Summer Olympics",
        "noc": "ITA",
        "discipline": "Boxing",
        "event": "Light-Welterweight, Men\n(Olympic)",
        "medal": "Bronze"
      }
    ]
  },
  {
    "id": "4890",
    "name": "David•Tua",
    "born": "21 November 1972 in Faleasiu, A'ana (SAM)",
    "measurements": "180 cm / 91 kg",
    "medals": [
      {
        "game": "1992 Summer Olympics",
        "noc": "NZL",
        "discipline": "Boxing",
        "event": "Heavyweight, Men\n(Olympic)",
        "medal": "Bronze"
      }
    ]
  },
  {
    "id": "4990",
    "name": "Pascual•Pérez",
    "born": "4 May 1926 in Tupungato, Mendoza (ARG)",
    "measurements": {},
    "medals": [
      {
        "game": "1948 Summer Olympics",
        "noc": "ARG",
        "discipline": "Boxing",
        "event": "Flyweight, Men\n(Olympic)",
        "medal": "Gold"
      }
    ]
  },
  {
    "id": "5090",
    "name": "Wlamir•Marques",
    "born": "16 July 1936 in São Vicente, São Paulo (BRA)",
    "measurements": "185 cm / 80 kg",
    "medals": [
      {
        "game": "1960 Summer Olympics",
        "noc": "BRA",
        "discipline": "Basketball (Basketball)",
        "event": "Basketball, Men\n(Olympic)",
        "medal": "Bronze"
      },
      {
        "game": "1964 Summer Olympics",
        "noc": "BRA",
        "discipline": "Basketball (Basketball)",
        "event": "Basketball, Men\n(Olympic)",
        "medal": "Bronze"
      }
    ]
  },
  {
    "id": "5290",
    "name": "Todorka•Yordanova",
    "born": "3 January 1956",
    "measurements": "182 cm / 72 kg",
    "medals": [
      {
        "game": "1976 Summer Olympics",
        "noc": "BUL",
        "discipline": "Basketball (Basketball)",
        "event": "Basketball, Women\n(Olympic)",
        "medal": "Bronze"
      }
    ]
  },
  {
    "id": "5890",
    "name": "Victorio•Cieslinskas",
    "born": "27 October 1922 in ? (LTU)",
    "measurements": {},
    "medals": [
      {
        "game": "1952 Summer Olympics",
        "noc": "URU",
        "discipline": "Basketball (Basketball)",
        "event": "Basketball, Men\n(Olympic)",
        "medal": "Bronze"
      }
    ]
  },
  {
    "id": "7790",
    "name": "Janusz•Zarenkiewicz",
    "born": "3 August 1959 in Nowy Las, Opolskie (POL)",
    "measurements": "188 cm / 91 kg",
    "medals": [
      {
        "game": "1988 Summer Olympics",
        "noc": "POL",
        "discipline": "Boxing",
        "event": "Super-Heavyweight, Men\n(Olympic)",
        "medal": "Bronze"
      }
    ]
  },
  {
    "id": "7990",
    "name": "Dries•Niemann",
    "born": "12 August 1927 in Bloemfontein, Free State (RSA)",
    "measurements": {},
    "medals": [
      {
        "game": "1952 Summer Olympics",
        "noc": "RSA",
        "discipline": "Boxing",
        "event": "Heavyweight, Men\n(Olympic)",
        "medal": "Bronze"
      }
    ]
  },
  {
    "id": "8490",
    "name": "Yevgeny•Feofanov",
    "born": "22 April 1937 in Moskva (Moscow), Moskva (RUS)",
    "measurements": "173 cm / 75 kg",
    "medals": [
      {
        "game": "1960 Summer Olympics",
        "noc": "URS",
        "discipline": "Boxing",
        "event": "Middleweight, Men\n(Olympic)",
        "medal": "Bronze"
      }
    ]
  },
  {
    "id": "8790",
    "name": "Jesse•Valdez",
    "born": "12 July 1947 in Houston, Texas (USA)",
    "measurements": "174 cm / 67 kg",
    "medals": [
      {
        "game": "1972 Summer Olympics",
        "noc": "USA",
        "discipline": "Boxing",
        "event": "Welterweight, Men\n(Olympic)",
        "medal": "Bronze"
      }
    ]
  },
  {
    "id": "9190",
    "name": "Ivan•Burchin",
    "born": "9 December 1952 in Mizia, Vratsa (BUL)",
    "measurements": "174 cm / 80 kg",
    "medals": [
      {
        "game": "1972 Summer Olympics",
        "noc": "BUL",
        "discipline": "Canoe Sprint (Canoeing)",
        "event": "Canadian Doubles, 1,000 metres, Men\n(Olympic)",
        "medal": "Bronze"
      }
    ]
  },
  {
    "id": "9890",
    "name": "Thomas•Becker",
    "born": "6 July 1967 in Hilden, Nordrhein-Westfalen (GER)",
    "measurements": "192 cm / 85 kg",
    "medals": [
      {
        "game": "1996 Summer Olympics",
        "noc": "GER",
        "discipline": "Canoe Slalom (Canoeing)",
        "event": "Kayak Singles, Slalom, Men\n(Olympic)",
        "medal": "Bronze"
      }
    ]
  },
  {
    "id": "10090",
    "name": "János•Rátkai",
    "born": "30 May 1951 in Kunszentmiklós, Bács-Kiskun (HUN)",
    "measurements": "177 cm / 78 kg",
    "medals": [
      {
        "game": "1972 Summer Olympics",
        "noc": "HUN",
        "discipline": "Canoe Sprint (Canoeing)",
        "event": "Kayak Doubles, 1,000 metres, Men\n(Olympic)",
        "medal": "Silver"
      }
    ]
  },
  {
    "id": "10390",
    "name": "Steinar•Amundsen",
    "born": "4 July 1945 in Bærum, Viken (NOR)",
    "measurements": "195 cm / 88 kg",
    "medals": [
      {
        "game": "1968 Summer Olympics",
        "noc": "NOR",
        "discipline": "Canoe Sprint (Canoeing)",
        "event": "Kayak Fours, 1,000 metres, Men\n(Olympic)",
        "medal": "Gold"
      },
      {
        "game": "1972 Summer Olympics",
        "noc": "NOR",
        "discipline": "Canoe Sprint (Canoeing)",
        "event": "Kayak Fours, 1,000 metres, Men\n(Olympic)",
        "medal": "Bronze"
      }
    ]
  },
  {
    "id": "10490",
    "name": "Krzysztof•Kołomański",
    "born": "16 August 1973 in Opoczno, Łódzkie (POL)",
    "measurements": "169 cm / 69 kg",
    "medals": [
      {
        "game": "2000 Summer Olympics",
        "noc": "POL",
        "discipline": "Canoe Slalom (Canoeing)",
        "event": "Canadian Doubles, Slalom, Men\n(Olympic)",
        "medal": "Silver"
      }
    ]
  },
  {
    "id": "10990",
    "name": "Vladimir•Morozov",
    "born": "19 July 1952 in Novaya Dmitrovka, Moskva (RUS)",
    "measurements": "184 cm / 94 kg",
    "medals": [
      {
        "game": "1976 Summer Olympics",
        "noc": "URS",
        "discipline": "Canoe Sprint (Canoeing)",
        "event": "Kayak Fours, 1,000 metres, Men\n(Olympic)",
        "medal": "Gold"
      }
    ]
  },
  {
    "id": "11290",
    "name": "Leslie•Burr-Howard",
    "born": "1 October 1956 in Westport, Connecticut (USA)",
    "measurements": "167 cm / 55 kg",
    "medals": [
      {
        "game": "1984 Summer Olympics",
        "noc": "USA",
        "discipline": "Equestrian Jumping (Equestrian)",
        "event": "Team, Open\n(Olympic)",
        "medal": "Gold"
      },
      {
        "game": "1996 Summer Olympics",
        "noc": "USA",
        "discipline": "Equestrian Jumping (Equestrian)",
        "event": "Team, Open\n(Olympic)",
        "medal": "Silver"
      }
    ]
  },
  {
    "id": "11390",
    "name": "Karen•Lende O'Connor",
    "born": "17 February 1958 in The Plains, Virginia (USA)",
    "measurements": "168 cm / 55 kg",
    "medals": [
      {
        "game": "1996 Summer Olympics",
        "noc": "USA",
        "discipline": "Equestrian Eventing (Equestrian)",
        "event": "Team, Open\n(Olympic)",
        "medal": "Silver"
      },
      {
        "game": "2000 Summer Olympics",
        "noc": "USA",
        "discipline": "Equestrian Eventing (Equestrian)",
        "event": "Team, Open\n(Olympic)",
        "medal": "Bronze"
      }
    ]
  },
  {
    "id": "11490",
    "name": "Anky•van Grunsven",
    "born": "2 January 1968 in Erp, Noord-Brabant (NED)",
    "measurements": "172 cm / 56 kg",
    "medals": [
      {
        "game": "1992 Summer Olympics",
        "noc": "NED",
        "discipline": "Equestrian Dressage (Equestrian)",
        "event": "Team, Open\n(Olympic)",
        "medal": "Silver"
      },
      {
        "game": "1996 Summer Olympics",
        "noc": "NED",
        "discipline": "Equestrian Dressage (Equestrian)",
        "event": "Individual, Open\n(Olympic)",
        "medal": "Silver"
      },
      {
        "game": "1996 Summer Olympics",
        "noc": "NED",
        "discipline": "Equestrian Dressage (Equestrian)",
        "event": "Team, Open\n(Olympic)",
        "medal": "Silver"
      },
      {
        "game": "2000 Summer Olympics",
        "noc": "NED",
        "discipline": "Equestrian Dressage (Equestrian)",
        "event": "Individual, Open\n(Olympic)",
        "medal": "Gold"
      },
      {
        "game": "2000 Summer Olympics",
        "noc": "NED",
        "discipline": "Equestrian Dressage (Equestrian)",
        "event": "Team, Open\n(Olympic)",
        "medal": "Silver"
      },
      {
        "game": "2004 Summer Olympics",
        "noc": "NED",
        "discipline": "Equestrian Dressage (Equestrian)",
        "event": "Individual, Open\n(Olympic)",
        "medal": "Gold"
      },
      {
        "game": "2008 Summer Olympics",
        "noc": "NED",
        "discipline": "Equestrian Dressage (Equestrian)",
        "event": "Individual, Open\n(Olympic)",
        "medal": "Gold"
      },
      {
        "game": "2008 Summer Olympics",
        "noc": "NED",
        "discipline": "Equestrian Dressage (Equestrian)",
        "event": "Team, Open\n(Olympic)",
        "medal": "Silver"
      },
      {
        "game": "2012 Summer Olympics",
        "noc": "NED",
        "discipline": "Equestrian Dressage (Equestrian)",
        "event": "Team, Open\n(Olympic)",
        "medal": "Bronze"
      }
    ]
  },
  {
    "id": "11990",
    "name": "Folke•Frölén",
    "born": "25 February 1908 in Eskilstuna, Södermanland (SWE)",
    "measurements": {},
    "medals": [
      {
        "game": "1952 Summer Olympics",
        "noc": "SWE",
        "discipline": "Equestrian Eventing (Equestrian)",
        "event": "Team, Men\n(Olympic)",
        "medal": "Gold"
      }
    ]
  },
  {
    "id": "12290",
    "name": "Neale•Lavis",
    "born": "11 June 1930 in Murwillumbah, New South Wales (AUS)",
    "measurements": "171 cm / 73 kg",
    "medals": [
      {
        "game": "1960 Summer Olympics",
        "noc": "AUS",
        "discipline": "Equestrian Eventing (Equestrian)",
        "event": "Individual, Men\n(Olympic)",
        "medal": "Silver"
      },
      {
        "game": "1960 Summer Olympics",
        "noc": "AUS",
        "discipline": "Equestrian Eventing (Equestrian)",
        "event": "Team, Men\n(Olympic)",
        "medal": "Gold"
      }
    ]
  },
  {
    "id": "12490",
    "name": "Andrew•Nicholson",
    "born": "1 August 1961 in Te Awamutu, Waikato (NZL)",
    "measurements": "182 cm / 78 kg",
    "medals": [
      {
        "game": "1992 Summer Olympics",
        "noc": "NZL",
        "discipline": "Equestrian Eventing (Equestrian)",
        "event": "Team, Open\n(Olympic)",
        "medal": "Silver"
      },
      {
        "game": "1996 Summer Olympics",
        "noc": "NZL",
        "discipline": "Equestrian Eventing (Equestrian)",
        "event": "Team, Open\n(Olympic)",
        "medal": "Bronze"
      },
      {
        "game": "2012 Summer Olympics",
        "noc": "NZL",
        "discipline": "Equestrian Eventing (Equestrian)",
        "event": "Team, Open\n(Olympic)",
        "medal": "Bronze"
      }
    ]
  },
  {
    "id": "12890",
    "name": "Alberto•Valdés Lacarra",
    "born": "30 November 1950",
    "measurements": "178 cm / 65 kg",
    "medals": [
      {
        "game": "1980 Summer Olympics",
        "noc": "MEX",
        "discipline": "Equestrian Jumping (Equestrian)",
        "event": "Team, Open\n(Olympic)",
        "medal": "Bronze"
      }
    ]
  },
  {
    "id": "14390",
    "name": "Guido•Fulst",
    "born": "7 July 1970 in Wernigerode, Sachsen-Anhalt (GER)",
    "measurements": "180 cm / 78 kg",
    "medals": [
      {
        "game": "1992 Summer Olympics",
        "noc": "GER",
        "discipline": "Cycling Track (Cycling)",
        "event": "Team Pursuit, 4,000 metres, Men\n(Olympic)",
        "medal": "Gold"
      },
      {
        "game": "2000 Summer Olympics",
        "noc": "GER",
        "discipline": "Cycling Track (Cycling)",
        "event": "Team Pursuit, 4,000 metres, Men\n(Olympic)",
        "medal": "Gold"
      },
      {
        "game": "2004 Summer Olympics",
        "noc": "GER",
        "discipline": "Cycling Track (Cycling)",
        "event": "Points Race, Men\n(Olympic)",
        "medal": "Bronze"
      }
    ]
  },
  {
    "id": "14890",
    "name": "Bernard•Janssens",
    "born": "18 August 1895 in Hoboken, Antwerpen (BEL)",
    "measurements": {},
    "medals": [
      {
        "game": "1920 Summer Olympics",
        "noc": "BEL",
        "discipline": "Cycling Road (Cycling)",
        "event": "Road Race, Team, Men\n(Olympic)",
        "medal": "Bronze"
      }
    ]
  },
  {
    "id": "15390",
    "name": "Jørn•Lund",
    "born": "26 August 1944 in Astrup, Mariagerfjord, Nordjylland (DEN)",
    "measurements": "177 cm / 76 kg",
    "medals": [
      {
        "game": "1976 Summer Olympics",
        "noc": "DEN",
        "discipline": "Cycling Road (Cycling)",
        "event": "100 kilometres Team Time Trial, Men\n(Olympic)",
        "medal": "Bronze"
      }
    ]
  },
  {
    "id": "15890",
    "name": "Leonard Harvey•Nitz",
    "born": "20 September 1956 in Hamilton, Ohio (USA)",
    "measurements": "180 cm / 75 kg",
    "medals": [
      {
        "game": "1984 Summer Olympics",
        "noc": "USA",
        "discipline": "Cycling Track (Cycling)",
        "event": "Individual Pursuit, 4,000 metres, Men\n(Olympic)",
        "medal": "Bronze"
      },
      {
        "game": "1984 Summer Olympics",
        "noc": "USA",
        "discipline": "Cycling Track (Cycling)",
        "event": "Team Pursuit, 4,000 metres, Men\n(Olympic)",
        "medal": "Silver"
      }
    ]
  },
  {
    "id": "16090",
    "name": "Andrea•Peron",
    "born": "14 August 1971 in Varese, Varese (ITA)",
    "measurements": "183 cm / 70 kg",
    "medals": [
      {
        "game": "1992 Summer Olympics",
        "noc": "ITA",
        "discipline": "Cycling Road (Cycling)",
        "event": "100 kilometres Team Time Trial, Men\n(Olympic)",
        "medal": "Silver"
      }
    ]
  },
  {
    "id": "17090",
    "name": "Aleksandr•Vinokurov",
    "born": "16 September 1973 in Bishkul, Soltustyk Qazaqstan (KAZ)",
    "measurements": "177 cm / 68 kg",
    "medals": [
      {
        "game": "2000 Summer Olympics",
        "noc": "KAZ",
        "discipline": "Cycling Road (Cycling)",
        "event": "Road Race, Individual, Men\n(Olympic)",
        "medal": "Silver"
      },
      {
        "game": "2012 Summer Olympics",
        "noc": "KAZ",
        "discipline": "Cycling Road (Cycling)",
        "event": "Road Race, Individual, Men\n(Olympic)",
        "medal": "Gold"
      }
    ]
  },
  {
    "id": "17490",
    "name": "Lisa•Powell-Carruthers",
    "born": "8 July 1970 in Sydney, New South Wales (AUS)",
    "measurements": "168 cm / 60 kg",
    "medals": [
      {
        "game": "1996 Summer Olympics",
        "noc": "AUS",
        "discipline": "Hockey",
        "event": "Hockey, Women\n(Olympic)",
        "medal": "Gold"
      },
      {
        "game": "2000 Summer Olympics",
        "noc": "AUS",
        "discipline": "Hockey",
        "event": "Hockey, Women\n(Olympic)",
        "medal": "Gold"
      }
    ]
  },
  {
    "id": "17890",
    "name": "Charles•Gondouin",
    "born": "21 July 1875 in Paris Xe, Paris (FRA)",
    "measurements": "169 cm",
    "medals": [
      {
        "game": "1900 Summer Olympics",
        "noc": "FRA",
        "discipline": "Rugby (Rugby)",
        "event": "Rugby, Men\n(Olympic)",
        "medal": "Gold"
      },
      {
        "game": "1900 Summer Olympics",
        "noc": "FRA",
        "discipline": "Rugby (Rugby)",
        "event": "Tug-Of-War, Men\n(Olympic)",
        "medal": "Silver"
      }
    ]
  },
  {
    "id": "17990",
    "name": "Edmond•Bury",
    "born": "4 November 1884 in Kensington, England (GBR)",
    "measurements": {},
    "medals": [
      {
        "game": "1908 Summer Olympics",
        "noc": "GBR",
        "discipline": "Racquets",
        "event": "Doubles, Men\n(Olympic)",
        "medal": "Silver"
      }
    ]
  },
  {
    "id": "18090",
    "name": "Antonio•Nava",
    "born": "5 September 1905 in Ixcaquixtla, Puebla (MEX)",
    "measurements": {},
    "medals": [
      {
        "game": "1936 Summer Olympics",
        "noc": "MEX",
        "discipline": "Polo",
        "event": "Polo, Men\n(Olympic)",
        "medal": "Bronze"
      }
    ]
  },
  {
    "id": "18490",
    "name": "José Antonio•Dinarés",
    "born": "5 June 1940 in Terrassa, Barcelona (ESP)",
    "measurements": "175 cm / 68 kg",
    "medals": [
      {
        "game": "1960 Summer Olympics",
        "noc": "ESP",
        "discipline": "Hockey",
        "event": "Hockey, Men\n(Olympic)",
        "medal": "Bronze"
      }
    ]
  },
  {
    "id": "18690",
    "name": "Kath•Johnson",
    "born": "21 January 1967 in King's Lynn, England (GBR)",
    "measurements": "170 cm / 65 kg",
    "medals": [
      {
        "game": "1992 Summer Olympics",
        "noc": "GBR",
        "discipline": "Hockey",
        "event": "Hockey, Women\n(Olympic)",
        "medal": "Bronze"
      }
    ]
  },
  {
    "id": "18990",
    "name": "Tobias•Frank",
    "born": "5 April 1958 in Worms, Rheinland-Pfalz (GER)",
    "measurements": "178 cm / 73 kg",
    "medals": [
      {
        "game": "1984 Summer Olympics",
        "noc": "FRG",
        "discipline": "Hockey",
        "event": "Hockey, Men\n(Olympic)",
        "medal": "Silver"
      },
      {
        "game": "1988 Summer Olympics",
        "noc": "FRG",
        "discipline": "Hockey",
        "event": "Hockey, Men\n(Olympic)",
        "medal": "Silver"
      }
    ]
  },
  {
    "id": "19690",
    "name": "Anneloes•Nieuwenhuizen",
    "born": "16 October 1963 in Bussum, Noord-Holland (NED)",
    "measurements": "172 cm / 60 kg",
    "medals": [
      {
        "game": "1984 Summer Olympics",
        "noc": "NED",
        "discipline": "Hockey",
        "event": "Hockey, Women\n(Olympic)",
        "medal": "Gold"
      },
      {
        "game": "1988 Summer Olympics",
        "noc": "NED",
        "discipline": "Hockey",
        "event": "Hockey, Women\n(Olympic)",
        "medal": "Bronze"
      }
    ]
  },
  {
    "id": "20290",
    "name": "Nataliya•Bykova",
    "born": "17 August 1958",
    "measurements": "160 cm / 59 kg",
    "medals": [
      {
        "game": "1980 Summer Olympics",
        "noc": "URS",
        "discipline": "Hockey",
        "event": "Hockey, Women\n(Olympic)",
        "medal": "Bronze"
      }
    ]
  },
  {
    "id": "20390",
    "name": "Amos•Deacon",
    "born": "28 May 1904 in Philadelphia, Pennsylvania (USA)",
    "measurements": {},
    "medals": [
      {
        "game": "1932 Summer Olympics",
        "noc": "USA",
        "discipline": "Hockey",
        "event": "Hockey, Men\n(Olympic)",
        "medal": "Bronze"
      }
    ]
  },
  {
    "id": "21190",
    "name": "Milan•Neralić",
    "born": "26 February 1875 in Slunj, Karlovačka županija (CRO)",
    "measurements": {},
    "medals": [
      {
        "game": "1900 Summer Olympics",
        "noc": "AUT",
        "discipline": "Fencing",
        "event": "Sabre, Masters, Individual, Men\n(Olympic)",
        "medal": "Bronze"
      }
    ]
  },
  {
    "id": "21690",
    "name": "Risto•Hurme",
    "born": "16 May 1950 in Turku, Varsinais-Suomi (FIN)",
    "measurements": "180 cm / 73 kg",
    "medals": [
      {
        "game": "1972 Summer Olympics",
        "noc": "FIN",
        "discipline": "Fencing",
        "event": "Team, Men\n(Olympic)",
        "medal": "Bronze"
      }
    ]
  },
  {
    "id": "21790",
    "name": "Jacky•Courtillat",
    "born": "8 January 1943 in Melun, Seine-et-Marne (FRA)",
    "measurements": "169 cm / 68 kg",
    "medals": [
      {
        "game": "1964 Summer Olympics",
        "noc": "FRA",
        "discipline": "Fencing",
        "event": "Foil, Team, Men\n(Olympic)",
        "medal": "Bronze"
      }
    ]
  },
  {
    "id": "21890",
    "name": "Jean-Michel•Henry",
    "born": "14 December 1963 in Marseille (Marseilles), Bouches-du-Rhône (FRA)",
    "measurements": "186 cm / 82 kg",
    "medals": [
      {
        "game": "1984 Summer Olympics",
        "noc": "FRA",
        "discipline": "Fencing",
        "event": "Épée, Team, Men\n(Olympic)",
        "medal": "Silver"
      },
      {
        "game": "1988 Summer Olympics",
        "noc": "FRA",
        "discipline": "Fencing",
        "event": "Épée, Team, Men\n(Olympic)",
        "medal": "Gold"
      },
      {
        "game": "1992 Summer Olympics",
        "noc": "FRA",
        "discipline": "Fencing",
        "event": "Épée, Individual, Men\n(Olympic)",
        "medal": "Bronze"
      },
      {
        "game": "1996 Summer Olympics",
        "noc": "FRA",
        "discipline": "Fencing",
        "event": "Épée, Team, Men\n(Olympic)",
        "medal": "Bronze"
      }
    ]
  },
  {
    "id": "22190",
    "name": "Edgar•Seligman",
    "born": "14 April 1867 in San Francisco, California (USA)",
    "measurements": "174 cm / 80 kg",
    "medals": [
      {
        "game": "1906  Intercalated Games",
        "noc": "GBR",
        "discipline": "Fencing",
        "event": "Épée, Team, Men\n(Intercalated)",
        "medal": "Silver"
      },
      {
        "game": "1908 Summer Olympics",
        "noc": "GBR",
        "discipline": "Fencing",
        "event": "Épée, Team, Men\n(Olympic)",
        "medal": "Silver"
      },
      {
        "game": "1912 Summer Olympics",
        "noc": "GBR",
        "discipline": "Fencing",
        "event": "Épée, Team, Men\n(Olympic)",
        "medal": "Silver"
      }
    ]
  },
  {
    "id": "22490",
    "name": "József•Marosi",
    "born": "16 October 1934 in Budapest, Budapest (HUN)",
    "measurements": "180 cm / 85 kg",
    "medals": [
      {
        "game": "1956 Summer Olympics",
        "noc": "HUN",
        "discipline": "Fencing",
        "event": "Foil, Team, Men\n(Olympic)",
        "medal": "Bronze"
      },
      {
        "game": "1956 Summer Olympics",
        "noc": "HUN",
        "discipline": "Fencing",
        "event": "Épée, Team, Men\n(Olympic)",
        "medal": "Silver"
      }
    ]
  },
  {
    "id": "22690",
    "name": "Aldo•Montano",
    "born": "23 November 1910 in Livorno, Livorno (ITA)",
    "measurements": {},
    "medals": [
      {
        "game": "1936 Summer Olympics",
        "noc": "ITA",
        "discipline": "Fencing",
        "event": "Sabre, Team, Men\n(Olympic)",
        "medal": "Silver"
      },
      {
        "game": "1948 Summer Olympics",
        "noc": "ITA",
        "discipline": "Fencing",
        "event": "Sabre, Team, Men\n(Olympic)",
        "medal": "Silver"
      }
    ]
  },
  {
    "id": "23190",
    "name": "João•Sassetti",
    "born": "22 January 1892 in Lisboa, Distrito de Lisboa (POR)",
    "measurements": {},
    "medals": [
      {
        "game": "1928 Summer Olympics",
        "noc": "POR",
        "discipline": "Fencing",
        "event": "Épée, Team, Men\n(Olympic)",
        "medal": "Bronze"
      }
    ]
  },
  {
    "id": "23290",
    "name": "Ilgar•Mamedov",
    "born": "15 November 1965 in Bakı, Bakı (AZE)",
    "measurements": "183 cm / 83 kg",
    "medals": [
      {
        "game": "1988 Summer Olympics",
        "noc": "URS",
        "discipline": "Fencing",
        "event": "Foil, Team, Men\n(Olympic)",
        "medal": "Gold"
      },
      {
        "game": "1996 Summer Olympics",
        "noc": "RUS",
        "discipline": "Fencing",
        "event": "Foil, Team, Men\n(Olympic)",
        "medal": "Gold"
      }
    ]
  },
  {
    "id": "23690",
    "name": "Miguel•de Capriles",
    "born": "30 November 1906 in Ciudad de México (Mexico City), Ciudad de México (MEX)",
    "measurements": {},
    "medals": [
      {
        "game": "1932 Summer Olympics",
        "noc": "USA",
        "discipline": "Fencing",
        "event": "Épée, Team, Men\n(Olympic)",
        "medal": "Bronze"
      },
      {
        "game": "1948 Summer Olympics",
        "noc": "USA",
        "discipline": "Fencing",
        "event": "Sabre, Team, Men\n(Olympic)",
        "medal": "Bronze"
      }
    ]
  },
  {
    "id": "24290",
    "name": "Milko•Gaydarski",
    "born": "18 March 1946 in Sofia, Sofia Grad (BUL)",
    "measurements": "180 cm / 72 kg",
    "medals": [
      {
        "game": "1968 Summer Olympics",
        "noc": "BUL",
        "discipline": "Football (Football)",
        "event": "Football, Men\n(Olympic)",
        "medal": "Silver"
      }
    ]
  },
  {
    "id": "24690",
    "name": "Bjørn•Rasmussen",
    "born": "19 May 1885 in København (Copenhagen), Hovedstaden (DEN)",
    "measurements": {},
    "medals": [
      {
        "game": "1908 Summer Olympics",
        "noc": "DEN",
        "discipline": "Football (Football)",
        "event": "Football, Men\n(Olympic)",
        "medal": "Silver"
      }
    ]
  },
  {
    "id": "25690",
    "name": "János•Farkas",
    "born": "27 March 1942 in Budapest, Budapest (HUN)",
    "measurements": "172 cm / 72 kg",
    "medals": [
      {
        "game": "1964 Summer Olympics",
        "noc": "HUN",
        "discipline": "Football (Football)",
        "event": "Football, Men\n(Olympic)",
        "medal": "Gold"
      }
    ]
  },
  {
    "id": "25990",
    "name": "Elvio•Banchero",
    "born": "28 April 1904 in Alessandria, Alessandria (ITA)",
    "measurements": {},
    "medals": [
      {
        "game": "1928 Summer Olympics",
        "noc": "ITA",
        "discipline": "Football (Football)",
        "event": "Football, Men\n(Olympic)",
        "medal": "Bronze"
      }
    ]
  },
  {
    "id": "26790",
    "name": "Hege•Riise",
    "born": "18 July 1969 in Lørenskog, Viken (NOR)",
    "measurements": "165 cm / 62 kg",
    "medals": [
      {
        "game": "1996 Summer Olympics",
        "noc": "NOR",
        "discipline": "Football (Football)",
        "event": "Football, Women\n(Olympic)",
        "medal": "Bronze"
      },
      {
        "game": "2000 Summer Olympics",
        "noc": "NOR",
        "discipline": "Football (Football)",
        "event": "Football, Women\n(Olympic)",
        "medal": "Gold"
      }
    ]
  },
  {
    "id": "27290",
    "name": "Lennart•Samuelsson",
    "born": "4 July 1924 in Borgstena, Borås, Västra Götaland (SWE)",
    "measurements": {},
    "medals": [
      {
        "game": "1952 Summer Olympics",
        "noc": "SWE",
        "discipline": "Football (Football)",
        "event": "Football, Men\n(Olympic)",
        "medal": "Bronze"
      }
    ]
  },
  {
    "id": "27390",
    "name": "Anton•Urban",
    "born": "16 January 1934 in Kysak, Košice (SVK)",
    "measurements": "175 cm / 74 kg",
    "medals": [
      {
        "game": "1964 Summer Olympics",
        "noc": "TCH",
        "discipline": "Football (Football)",
        "event": "Football, Men\n(Olympic)",
        "medal": "Silver"
      }
    ]
  }
]
