[
  {
    "id": "335",
    "name": "Pierre•Van Tilt",
    "born": {},
    "measurements": {},
    "medals": [
      {
        "game": "1920 Summer Olympics",
        "noc": "BEL",
        "discipline": "Archery",
        "event": "Target Archery, 28 metres, Team, Men\n(Olympic)",
        "medal": "Silver"
      },
      {
        "game": "1920 Summer Olympics",
        "noc": "BEL",
        "discipline": "Archery",
        "event": "Target Archery, 33 metres, Team, Men\n(Olympic)",
        "medal": "Gold"
      },
      {
        "game": "1920 Summer Olympics",
        "noc": "BEL",
        "discipline": "Archery",
        "event": "Target Archery, 50 metres, Team, Men\n(Olympic)",
        "medal": "Gold"
      }
    ]
  },
  {
    "id": "435",
    "name": "Päivi•Meriluoto-Aaltonen",
    "born": "12 December 1952 in Tampere, Pirkanmaa (FIN)",
    "measurements": "171 cm / 61 kg",
    "medals": [
      {
        "game": "1980 Summer Olympics",
        "noc": "FIN",
        "discipline": "Archery",
        "event": "Individual, Women\n(Olympic)",
        "medal": "Bronze"
      }
    ]
  },
  {
    "id": "2235",
    "name": "Butch•Johnson",
    "born": "30 August 1955 in Worcester, Massachusetts (USA)",
    "measurements": "191 cm / 98 kg",
    "medals": [
      {
        "game": "1996 Summer Olympics",
        "noc": "USA",
        "discipline": "Archery",
        "event": "Team, Men\n(Olympic)",
        "medal": "Gold"
      },
      {
        "game": "2000 Summer Olympics",
        "noc": "USA",
        "discipline": "Archery",
        "event": "Team, Men\n(Olympic)",
        "medal": "Bronze"
      }
    ]
  },
  {
    "id": "2835",
    "name": "Dragutin•Čermak",
    "born": "12 October 1944 in Beograd (Belgrade), Beograd (SRB)",
    "measurements": "190 cm / 92 kg",
    "medals": [
      {
        "game": "1968 Summer Olympics",
        "noc": "YUG",
        "discipline": "Basketball (Basketball)",
        "event": "Basketball, Men\n(Olympic)",
        "medal": "Silver"
      }
    ]
  },
  {
    "id": "3035",
    "name": "Jean•Gachet",
    "born": "2 June 1894 in Saint-Étienne, Loire (FRA)",
    "measurements": null,
    "medals": [
      {
        "game": "1920 Summer Olympics",
        "noc": "FRA",
        "discipline": "Boxing",
        "event": "Featherweight, Men\n(Olympic)",
        "medal": "Silver"
      }
    ]
  }
]
